bill_flow/__init__.py
bill_flow-0.0.2.dist-info/METADATA
bill_flow-0.0.2.dist-info/WHEEL
bill_flow-0.0.2.dist-info/licenses/LICENSE
bill_flow-0.0.2.dist-info/RECORD
