Metadata-Version: 2.4
Name: bill-flow
Version: 0.0.2
Summary: A package to create plugins for bill-flow system
Project-URL: Homepage, https://github.com/raulodev/bill-flow
Project-URL: Issues, https://github.com/raulodev/bill-flow/issues
Author-email: Raul Cobiellas <raulodev@gmail.com>
License-Expression: MIT
License-File: LICENSE
Classifier: Operating System :: OS Independent
Classifier: Programming Language :: Python :: 3
Requires-Python: >=3.9
Requires-Dist: pluggy==1.6.0
